python_servicecontainer-1.0.2.dist-info/DESCRIPTION.rst
python_servicecontainer-1.0.2.dist-info/METADATA
python_servicecontainer-1.0.2.dist-info/metadata.json
python_servicecontainer-1.0.2.dist-info/RECORD
python_servicecontainer-1.0.2.dist-info/top_level.txt
python_servicecontainer-1.0.2.dist-info/WHEEL
servicecontainer/__init__.py
servicecontainer/container.py
servicecontainer/service.py
