Metadata-Version: 2.0
Name: python-servicecontainer
Version: 1.0.2
Summary: A simple and small service container
Home-page: https://github.com/zerodine/python-ServiceContainer
Author: Thomas Spycher
Author-email: tspycher@zerodine.com
License: MIT
Keywords: container di service
Platform: UNKNOWN
Classifier: Development Status :: 5 - Production/Stable
Classifier: Intended Audience :: Developers
Classifier: License :: OSI Approved :: MIT License
Classifier: Programming Language :: Python :: 2
Classifier: Programming Language :: Python :: 2.6
Classifier: Programming Language :: Python :: 2.7
